LICENSE.txt
README.md
setup.cfg
setup.py
AESRLib/AESRandomizer.py
AESRLib/ErrChecker.py
AESRLib/FileHandler.py
AESRLib/KMI.py
AESRLib/Randomizer.py
AESRLib/__init__.py
AESRLib.egg-info/PKG-INFO
AESRLib.egg-info/SOURCES.txt
AESRLib.egg-info/dependency_links.txt
AESRLib.egg-info/requires.txt
AESRLib.egg-info/top_level.txt