Metadata-Version: 2.1
Name: AESRLib
Version: 1.0
Summary: Crypto package based on variable key leveraging combo of AES and Randomization!
Home-page: https://github.com/me-yutakun/AESRLib
Download-URL: https://github.com/me-yutakun/AESRLib/archive/refs/tags/v1.0.tar.gz
Author: Shubham Chakraborty
Author-email: cosmoscandium@gmail.com
License: MIT
Keywords: AES,Random,base64
Classifier: Development Status :: 4 - Beta
Classifier: Intended Audience :: Developers
Classifier: Topic :: Security :: Cryptography
Classifier: License :: OSI Approved :: MIT License
Classifier: Programming Language :: Python :: 3.10
Requires-Python: >=3.10
License-File: LICENSE.txt
